calc_work_hours/__init__.py
calc_work_hours/controller.py
calc_work_hours/json_utils.py
calc_work_hours/main.py
calc_work_hours/schema.py
calc_work_hours/utils.py
workhourcalc-0.0.1.dist-info/METADATA
workhourcalc-0.0.1.dist-info/WHEEL
workhourcalc-0.0.1.dist-info/top_level.txt
workhourcalc-0.0.1.dist-info/RECORD
